[{"homeTeam":"HJK","awayTeam":"VPS","bookmakers":{"pinnacle":{"home":1.92,"draw":4.13,"away":3.46,"overUnder":{"3":{"over":1.98,"under":1.86}}},"onexbet":{"home":1.88,"draw":4,"away":3.5,"overUnder":{"2.5":{"over":1.58,"under":2.33}}},"marathonbet":{"home":1.86,"draw":4,"away":3.52,"overUnder":{}},"unibet_fr":{"home":1.76,"draw":3.45,"away":3.2,"overUnder":{}},"pmu_fr":{"home":1.8,"draw":3.5,"away":3.4,"overUnder":{"2.5":{"over":1.56,"under":2.02}}},"unibet_se":{"home":1.88,"draw":3.65,"away":3.55,"overUnder":{"2.5":{"over":1.63,"under":2.1}}},"unibet_nl":{"home":1.88,"draw":3.65,"away":3.55,"overUnder":{"2.5":{"over":1.63,"under":2.1}}},"leovegas_se":{"home":1.85,"draw":3.65,"away":3.55,"overUnder":{}},"nordicbet":{"home":1.92,"draw":3.55,"away":3.7,"overUnder":{"2.5":{"over":1.65,"under":2.18}}},"betsson":{"home":1.92,"draw":3.55,"away":3.7,"overUnder":{"2.5":{"over":1.65,"under":2.18}}},"sport888":{"home":1.85,"draw":3.8,"away":3.4,"overUnder":{}},"williamhill":{"home":1.85,"draw":3.8,"away":3.4,"overUnder":{"2.5":{"over":1.55,"under":2.3}}},"betonlineag":{"home":1.9,"draw":4,"away":3.4,"overUnder":{"2.75":{"over":1.74,"under":2.15}}},"gtbets":{"home":1.9,"draw":3.98,"away":3.53,"overUnder":{"2.5":{"over":1.58,"under":2.33}}},"tipico_de":{"home":1.83,"draw":3.9,"away":3.5,"overUnder":{"2.5":{"over":1.55,"under":2.3}}},"everygame":{"home":1.8,"draw":3.85,"away":3.2,"overUnder":{}},"coolbet":{"home":2.08,"draw":3.75,"away":3.4,"overUnder":{"3":{"over":1.98,"under":1.87}}}}},{"homeTeam":"AC Oulu","awayTeam":"IF Gnistan","bookmakers":{"leovegas_se":{"home":2.1,"draw":3.45,"away":3.1,"overUnder":{}},"pmu_fr":{"home":2.02,"draw":3.3,"away":2.95,"overUnder":{"2.5":{"over":1.66,"under":1.88}}},"unibet_se":{"home":2.1,"draw":3.45,"away":3.1,"overUnder":{"2.5":{"over":1.73,"under":1.95}}},"unibet_nl":{"home":2.1,"draw":3.45,"away":3.1,"overUnder":{"2.5":{"over":1.73,"under":1.95}}},"unibet_fr":{"home":1.99,"draw":3.25,"away":2.8,"overUnder":{}},"onexbet":{"home":2.19,"draw":3.56,"away":3.02,"overUnder":{"2.5":{"over":1.74,"under":2.05}}},"nordicbet":{"home":2.08,"draw":3.7,"away":3.05,"overUnder":{"2.5":{"over":1.75,"under":1.98}}},"betsson":{"home":2.08,"draw":3.7,"away":3.05,"overUnder":{"2.5":{"over":1.75,"under":1.98}}},"betonlineag":{"home":2.2,"draw":3.65,"away":2.96,"overUnder":{"2.75":{"over":1.96,"under":1.86}}},"marathonbet":{"home":2.17,"draw":3.56,"away":3.02,"overUnder":{}},"pinnacle":{"home":2.19,"draw":3.75,"away":3.05,"overUnder":{"2.75":{"over":1.95,"under":1.88}}},"sport888":{"home":2.15,"draw":3.5,"away":3,"overUnder":{}},"williamhill":{"home":2.15,"draw":3.5,"away":3,"overUnder":{"2.5":{"over":1.75,"under":1.95}}},"gtbets":{"home":2.23,"draw":3.56,"away":3.02,"overUnder":{"2.5":{"over":1.75,"under":2.05}}},"tipico_de":{"home":2.1,"draw":3.5,"away":3.1,"overUnder":{"2.5":{"over":1.7,"under":2}}},"everygame":{"home":2.05,"draw":3.45,"away":2.8,"overUnder":{}},"coolbet":{"home":2.05,"draw":3.8,"away":3.45,"overUnder":{"2.5":{"over":1.74,"under":2.15}}}}},{"homeTeam":"SJK","awayTeam":"KuPS","bookmakers":{"betsson":{"home":3.35,"draw":3.55,"away":2.02,"overUnder":{"2.5":{"over":1.58,"under":2.28}}},"leovegas_se":{"home":3.25,"draw":3.5,"away":2,"overUnder":{}},"pmu_fr":{"home":3.1,"draw":3.35,"away":1.93,"overUnder":{"2.5":{"over":1.55,"under":2.04}}},"nordicbet":{"home":3.35,"draw":3.55,"away":2.02,"overUnder":{"2.5":{"over":1.58,"under":2.28}}},"unibet_nl":{"home":3.25,"draw":3.5,"away":2.02,"overUnder":{"2.5":{"over":1.63,"under":2.12}}},"unibet_se":{"home":3.25,"draw":3.5,"away":2.02,"overUnder":{"2.5":{"over":1.63,"under":2.12}}},"unibet_fr":{"home":2.9,"draw":3.35,"away":1.91,"overUnder":{}},"onexbet":{"home":3.1,"draw":3.72,"away":2.1,"overUnder":{"2.5":{"over":1.57,"under":2.35}}},"marathonbet":{"home":3.1,"draw":3.72,"away":2.08,"overUnder":{}},"betonlineag":{"home":3.05,"draw":3.75,"away":2.1,"overUnder":{"2.75":{"over":1.71,"under":2.2}}},"pinnacle":{"home":3.07,"draw":3.9,"away":2.14,"overUnder":{"3":{"over":1.93,"under":1.9}}},"sport888":{"home":3,"draw":3.6,"away":2.1,"overUnder":{}},"williamhill":{"home":3,"draw":3.6,"away":2.1,"overUnder":{"2.5":{"over":1.55,"under":2.3}}},"gtbets":{"home":3.27,"draw":3.78,"away":2.12,"overUnder":{"2.5":{"over":1.57,"under":2.36}}},"tipico_de":{"home":3.5,"draw":3.5,"away":1.93,"overUnder":{"3.5":{"over":2.3,"under":1.55}}},"everygame":{"home":2.85,"draw":3.6,"away":2,"overUnder":{}},"coolbet":{"home":3.13,"draw":3.75,"away":2.2,"overUnder":{"3":{"over":1.96,"under":1.89}}}}},{"homeTeam":"FF Jaro","awayTeam":"Inter Turku","bookmakers":{"unibet_fr":{"home":4.8,"draw":3.75,"away":1.42,"overUnder":{}},"onexbet":{"home":6.06,"draw":4.25,"away":1.5,"overUnder":{"2.5":{"over":1.7,"under":2.11}}},"unibet_nl":{"home":5.75,"draw":4.1,"away":1.48,"overUnder":{"2.5":{"over":1.66,"under":2.07}}},"betsson":{"home":5.9,"draw":3.95,"away":1.55,"overUnder":{"2.5":{"over":1.7,"under":2.08}}},"unibet_se":{"home":5.75,"draw":4.1,"away":1.48,"overUnder":{"2.5":{"over":1.66,"under":2.07}}},"leovegas_se":{"home":5.75,"draw":4.1,"away":1.47,"overUnder":{}},"pmu_fr":{"home":5.5,"draw":3.95,"away":1.42,"overUnder":{"2.5":{"over":1.57,"under":1.97}}},"nordicbet":{"home":5.9,"draw":3.95,"away":1.55,"overUnder":{"2.5":{"over":1.7,"under":2.08}}},"coolbet":{"home":5.5,"draw":4.5,"away":1.57,"overUnder":{"2.5":{"over":1.73,"under":2.17}}},"pinnacle":{"home":6.18,"draw":4.29,"away":1.51,"overUnder":{"2.75":{"over":1.9,"under":1.93}}},"marathonbet":{"home":6.05,"draw":4.25,"away":1.49,"overUnder":{}},"sport888":{"home":5.5,"draw":4,"away":1.5,"overUnder":{}},"williamhill":{"home":5.5,"draw":4,"away":1.5,"overUnder":{"2.5":{"over":1.65,"under":2.15}}},"tipico_de":{"home":6.5,"draw":4,"away":1.47,"overUnder":{"2.5":{"over":1.65,"under":2.1}}},"gtbets":{"home":5.8,"draw":4.33,"away":1.52,"overUnder":{"2.5":{"over":1.68,"under":2.15}}},"everygame":{"home":5.5,"draw":3.9,"away":1.45,"overUnder":{}}}}]